pydatadroid/__init__.py
pydatadroid/lib.py
pydatadroid/exceptions/__init__.py
pydatadroid/exceptions/execption.py
pydatadroid/protos/__init__.py
pydatadroid/protos/result_pb2.py
pydatadroid/source_processors/__init__.py
pydatadroid/source_processors/aws_cloudwatch_processor.py
pydatadroid/source_processors/azure_processor.py
pydatadroid/source_processors/bash_processor.py
pydatadroid/source_processors/clickhouse_db_processor.py
pydatadroid/source_processors/datadog_processor.py
pydatadroid/source_processors/db_connection_string_processor.py
pydatadroid/source_processors/eks_processor.py
pydatadroid/source_processors/elastic_search_provcessor.py
pydatadroid/source_processors/gke_processor.py
pydatadroid/source_processors/grafana_loki_processor.py
pydatadroid/source_processors/grafana_mimir_processor.py
pydatadroid/source_processors/grafana_promql_processor.py
pydatadroid/source_processors/kubectl_processor.py
pydatadroid/source_processors/new_relic_processor.py
pydatadroid/source_processors/postgres_db_processor.py
pydatadroid/source_processors/processor.py
pydatadroid/utils/__init__.py
pydatadroid/utils/proto_utils.py
pydatadroid/utils/time_utils.py
data_droid_sdk-0.0.2.dist-info/LICENSE
data_droid_sdk-0.0.2.dist-info/METADATA
data_droid_sdk-0.0.2.dist-info/WHEEL
data_droid_sdk-0.0.2.dist-info/top_level.txt
data_droid_sdk-0.0.2.dist-info/RECORD
